{"guide_basic_comments.md":"c5dee796","guide_basic_data-type-conversion.md":"b533cc4b","guide_basic_else.md":"c74adfe3","guide_basic_escape-character.md":"5affdd5e","guide_basic_function-input.md":"56dd5c1f","guide_basic_function-print.md":"87d0f26d","guide_basic_function-range.md":"118a6999","guide_basic_function-zip.md":"f15c31d9","guide_basic_if-elif-else.md":"15263f26","guide_basic_install-python.md":"3c422d3b","guide_basic_operator.md":"b6c7416a","guide_basic_pass.md":"d16b09da","guide_basic_reserved-word.md":"57bc53cd","guide_basic_type-of-data.md":"55fff442","guide_basic_variable.md":"8e887d9a","guide_basic_while-and-for-in.md":"2401e737","guide_dict_create.md":"04753024","guide_dict_delete.md":"604d7451","guide_dict_find.md":"9aff6253","guide_dict_index.md":"15345cd1","guide_dict_update.md":"245d190f","guide_list_create.md":"91deaccb","guide_list_delete.md":"0b2a0df0","guide_list_find.md":"5bfc8c6b","guide_list_index.md":"300a6c02","guide_list_sort.md":"05620455","guide_list_update.md":"4deaa78e","index.md":"f82ca459"}
